[
  { "w":1, "v":"{$name=Bilbar}"},
  { "w":1, "v":"{$name=Bilcorin}"},
  { "w":1, "v":"{$name=Bilgrim}"},
  { "w":1, "v":"{$name=Briwor}"},
  { "w":1, "v":"{$name=Orpip}"},
  { "w":1, "v":"{$name=Orros}"},
  { "w":1, "v":"{$name=Panaziver}"},
  { "w":1, "v":"{$name=Podon}"},
  { "w":1, "v":"{$name=Quoji}"},
  { "w":1, "v":"{$name=Wrezu}"},
  { "w":1, "v":"{$name=Orutor}"},
  { "w":1, "v":"{$name=Oruver}"},
  { "w":1, "v":"{$name=Yexim}"},
  { "w":1, "v":"{$name=Yosston}"},
  { "w":1, "v":"{$name=Enitix}"},
  { "w":1, "v":"{$name=Felver}"},
  { "w":1, "v":"{$name=Grapip}"},
  { "w":1, "v":"{$name=Hisni}"},
  { "w":1, "v":"{$name=Histix}"},
  { "w":1, "v":"{$name=Horhik}"},
  { "w":1, "v":"{$name=Ianlin}"}
]